find_step/__init__.py
find_step/__init__.pyi
find_step/_slow_and_simple.py
find_step/py.typed
find_step-0.0.2.dist-info/licenses/LICENSES/MIT.txt
find_step-0.0.2.dist-info/WHEEL
find_step-0.0.2.dist-info/METADATA
find_step-0.0.2.dist-info/RECORD
