Metadata-Version: 2.4
Name: find-step
Version: 0.0.2
Summary: All the str.find() goodness, now with a step argument
Author: Alex Willmer
Author-email: Alex Willmer <alex@moreati.org.uk>
License-Expression: MIT
License-File: LICENSES/MIT.txt
Classifier: Development Status :: 3 - Alpha
Classifier: Intended Audience :: Developers
Classifier: License :: OSI Approved :: Python Software Foundation License
Classifier: Operating System :: OS Independent
Classifier: Programming Language :: Python :: 3 :: Only
Classifier: Programming Language :: Python :: 3.10
Classifier: Programming Language :: Python :: 3.11
Classifier: Programming Language :: Python :: 3.12
Classifier: Programming Language :: Python :: 3.13
Classifier: Programming Language :: Python :: 3.14
Classifier: Typing :: Typed
Requires-Python: >=3.10
Project-URL: Homepage, https://github.com/moreati/find-step/
